pflotranutils/encapsulation/factory/__init__.py
pflotranutils/encapsulation/factory/dataProcessing.py
pflotranutils/encapsulation/factory/parameters.py
pflotranutils/h5_output/calc/__init__.py
pflotranutils/h5_output/calc/cross_section.py
pflotranutils/h5_output/factory/__init__.py
pflotranutils/h5_output/factory/h5_output_class.py
pflotranutils/h5_output/input/__init__.py
pflotranutils-0.0.4.dist-info/LICENSE
pflotranutils-0.0.4.dist-info/METADATA
pflotranutils-0.0.4.dist-info/WHEEL
pflotranutils-0.0.4.dist-info/top_level.txt
pflotranutils-0.0.4.dist-info/RECORD
