Metadata-Version: 2.2
Name: pflotranutils
Version: 0.0.4
Summary: A package for processing PFLOTRAN output
Author-email: Christian Dewey <cdewey@udel.edu>
Project-URL: Homepage, https://github.com/deweycw/pflotran-utils
Project-URL: Issues, https://github.com/deweycw/pflotran-utils/issues
Classifier: Programming Language :: Python :: 3
Classifier: License :: OSI Approved :: MIT License
Classifier: Operating System :: OS Independent
Requires-Python: >=3.10
License-File: LICENSE
Requires-Dist: numpy
Requires-Dist: matplotlib
Requires-Dist: scipy
Requires-Dist: pandas
Requires-Dist: h5py
Requires-Dist: seaborn
